<?xml version="1.0" encoding="utf-8"?>
<clothing-items>
 <clothing>
  <id>
   718289061
  </id>
  <name>
   Lacoste Hat L-4608
  </name>
  <category>
   Hat
  </category>
  <size>
   XL
  </size>
  <color>
   Оранжевый
  </color>
  <material>
   Шерсть
  </material>
  <price>
   715630
  </price>
  <rating>
   2.82
  </rating>
  <reviews>
   810782
  </reviews>
  <new>
   -
  </new>
  <exclusive>
   yes
  </exclusive>
  <sporty>
   no
  </sporty>
 </clothing>
 <clothing>
  <id>
   236691265
  </id>
  <name>
   Reebok Shoes Y-7570
  </name>
  <category>
   Shoes
  </category>
  <size>
   S
  </size>
  <color>
   Фиолетовый
  </color>
  <material>
   Полиэстер
  </material>
  <price>
   683152
  </price>
  <rating>
   1.15
  </rating>
  <reviews>
   597921
  </reviews>
  <exclusive>
   no
  </exclusive>
 </clothing>
 <clothing>
  <id>
   558034867
  </id>
  <name>
   New Balance Gloves N-9419
  </name>
  <category>
   Gloves
  </category>
  <size>
   XXL
  </size>
  <color>
   Голубой
  </color>
  <material>
   Кожа
  </material>
  <price>
   674353
  </price>
  <rating>
   2.01
  </rating>
  <reviews>
   34332
  </reviews>
  <sporty>
   yes
  </sporty>
 </clothing>
 <clothing>
  <id>
   790334660
  </id>
  <name>
   Vans Blouse X-5588
  </name>
  <category>
   Blouse
  </category>
  <size>
   L
  </size>
  <color>
   Синий
  </color>
  <material>
   Хлопок
  </material>
  <price>
   314191
  </price>
  <rating>
   2.29
  </rating>
  <reviews>
   767162
  </reviews>
  <new>
   -
  </new>
  <sporty>
   yes
  </sporty>
 </clothing>
 <clothing>
  <id>
   542959774
  </id>
  <name>
   Nike T-shirt F-3954
  </name>
  <category>
   T-shirt
  </category>
  <size>
   M
  </size>
  <color>
   Фиолетовый
  </color>
  <material>
   Хлопок
  </material>
  <price>
   409689
  </price>
  <rating>
   3.82
  </rating>
  <reviews>
   207940
  </reviews>
  <exclusive>
   yes
  </exclusive>
 </clothing>
 <clothing>
  <id>
   923654486
  </id>
  <name>
   Addidas Handbags E-2469
  </name>
  <category>
   Handbags
  </category>
  <size>
   S
  </size>
  <color>
   Фиолетовый
  </color>
  <material>
   Полиэстер
  </material>
  <price>
   399199
  </price>
  <rating>
   4.76
  </rating>
  <reviews>
   446999
  </reviews>
  <exclusive>
   no
  </exclusive>
  <sporty>
   yes
  </sporty>
 </clothing>
 <clothing>
  <id>
   130579489
  </id>
  <name>
   DC Umbrellas F-2719
  </name>
  <category>
   Umbrellas
  </category>
  <size>
   XL
  </size>
  <color>
   Желтый
  </color>
  <material>
   Шерсть
  </material>
  <price>
   927238
  </price>
  <rating>
   3.98
  </rating>
  <reviews>
   840142
  </reviews>
  <new>
   +
  </new>
  <sporty>
   no
  </sporty>
 </clothing>
 <clothing>
  <id>
   975587274
  </id>
  <name>
   Puma Gloves T-9434
  </name>
  <category>
   Gloves
  </category>
  <size>
   XL
  </size>
  <color>
   Оранжевый
  </color>
  <material>
   Шерсть
  </material>
  <price>
   802250
  </price>
  <rating>
   4.28
  </rating>
  <reviews>
   616870
  </reviews>
  <new>
   +
  </new>
  <exclusive>
   no
  </exclusive>
  <sporty>
   no
  </sporty>
 </clothing>
 <clothing>
  <id>
   802352915
  </id>
  <name>
   Puma Handbags J-5109
  </name>
  <category>
   Handbags
  </category>
  <size>
   XL
  </size>
  <color>
   Красный
  </color>
  <material>
   Вискоза
  </material>
  <price>
   212667
  </price>
  <rating>
   3.04
  </rating>
  <reviews>
   891574
  </reviews>
  <exclusive>
   no
  </exclusive>
 </clothing>
 <clothing>
  <id>
   488480018
  </id>
  <name>
   Converse Umbrellas Z-4155
  </name>
  <category>
   Umbrellas
  </category>
  <size>
   S
  </size>
  <color>
   Красный
  </color>
  <material>
   Кожа
  </material>
  <price>
   586994
  </price>
  <rating>
   3.75
  </rating>
  <reviews>
   558252
  </reviews>
  <sporty>
   no
  </sporty>
 </clothing>
 <clothing>
  <id>
   225265025
  </id>
  <name>
   Vans Jeans I-9153
  </name>
  <category>
   Jeans
  </category>
  <size>
   XXL
  </size>
  <color>
   Голубой
  </color>
  <material>
   Кожа
  </material>
  <price>
   264190
  </price>
  <rating>
   1.7
  </rating>
  <reviews>
   436202
  </reviews>
  <new>
   +
  </new>
  <sporty>
   no
  </sporty>
 </clothing>
 <clothing>
  <id>
   222691668
  </id>
  <name>
   Converse Sweater P-8824
  </name>
  <category>
   Sweater
  </category>
  <size>
   M
  </size>
  <color>
   Зеленый
  </color>
  <material>
   Шерсть
  </material>
  <price>
   674981
  </price>
  <rating>
   2.13
  </rating>
  <reviews>
   967568
  </reviews>
  <sporty>
   no
  </sporty>
 </clothing>
 <clothing>
  <id>
   922068752
  </id>
  <name>
   Brooks Shoes B-4736
  </name>
  <category>
   Shoes
  </category>
  <size>
   L
  </size>
  <color>
   Синий
  </color>
  <material>
   Лен
  </material>
  <price>
   261996
  </price>
  <rating>
   1.54
  </rating>
  <reviews>
   122004
  </reviews>
  <exclusive>
   no
  </exclusive>
 </clothing>
 <clothing>
  <id>
   854235775
  </id>
  <name>
   Lacoste Shirt G-5219
  </name>
  <category>
   Shirt
  </category>
  <size>
   XL
  </size>
  <color>
   Фиолетовый
  </color>
  <material>
   Хлопок
  </material>
  <price>
   964157
  </price>
  <rating>
   2.77
  </rating>
  <reviews>
   21852
  </reviews>
  <new>
   -
  </new>
  <sporty>
   no
  </sporty>
 </clothing>
 <clothing>
  <id>
   146266090
  </id>
  <name>
   PleinSport Sweater H-3500
  </name>
  <category>
   Sweater
  </category>
  <size>
   L
  </size>
  <color>
   Желтый
  </color>
  <material>
   Лен
  </material>
  <price>
   984378
  </price>
  <rating>
   1.59
  </rating>
  <reviews>
   2990
  </reviews>
  <new>
   -
  </new>
  <exclusive>
   no
  </exclusive>
 </clothing>
 <clothing>
  <id>
   920248338
  </id>
  <name>
   Puma Jacket R-8776
  </name>
  <category>
   Jacket
  </category>
  <size>
   M
  </size>
  <color>
   Зеленый
  </color>
  <material>
   Шерсть
  </material>
  <price>
   483913
  </price>
  <rating>
   3.38
  </rating>
  <reviews>
   707226
  </reviews>
  <exclusive>
   yes
  </exclusive>
 </clothing>
 <clothing>
  <id>
   979428380
  </id>
  <name>
   DC Pants D-1217
  </name>
  <category>
   Pants
  </category>
  <size>
   XXL
  </size>
  <color>
   Фиолетовый
  </color>
  <material>
   Шелк
  </material>
  <price>
   152323
  </price>
  <rating>
   3.29
  </rating>
  <reviews>
   649433
  </reviews>
  <sporty>
   no
  </sporty>
 </clothing>
 <clothing>
  <id>
   433614637
  </id>
  <name>
   Asics Pants O-7099
  </name>
  <category>
   Pants
  </category>
  <size>
   S
  </size>
  <color>
   Фиолетовый
  </color>
  <material>
   Полиэстер
  </material>
  <price>
   331057
  </price>
  <rating>
   2.46
  </rating>
  <reviews>
   454119
  </reviews>
  <sporty>
   no
  </sporty>
 </clothing>
 <clothing>
  <id>
   288752153
  </id>
  <name>
   Puma Belts D-5938
  </name>
  <category>
   Belts
  </category>
  <size>
   XL
  </size>
  <color>
   Фиолетовый
  </color>
  <material>
   Вискоза
  </material>
  <price>
   113486
  </price>
  <rating>
   1.12
  </rating>
  <reviews>
   248307
  </reviews>
  <sporty>
   yes
  </sporty>
 </clothing>
 <clothing>
  <id>
   649689167
  </id>
  <name>
   Under Armour T-shirt Z-4626
  </name>
  <category>
   T-shirt
  </category>
  <size>
   L
  </size>
  <color>
   Голубой
  </color>
  <material>
   Кожа
  </material>
  <price>
   668305
  </price>
  <rating>
   1.01
  </rating>
  <reviews>
   38673
  </reviews>
  <new>
   +
  </new>
 </clothing>
 <clothing>
  <id>
   131724643
  </id>
  <name>
   Brooks Pants U-7937
  </name>
  <category>
   Pants
  </category>
  <size>
   XL
  </size>
  <color>
   Желтый
  </color>
  <material>
   Нейлон
  </material>
  <price>
   445083
  </price>
  <rating>
   1.48
  </rating>
  <reviews>
   318255
  </reviews>
  <new>
   +
  </new>
  <exclusive>
   yes
  </exclusive>
 </clothing>
 <clothing>
  <id>
   444829537
  </id>
  <name>
   Vans Pants F-5593
  </name>
  <category>
   Pants
  </category>
  <size>
   L
  </size>
  <color>
   Синий
  </color>
  <material>
   Кожа
  </material>
  <price>
   255803
  </price>
  <rating>
   1.56
  </rating>
  <reviews>
   942479
  </reviews>
  <new>
   +
  </new>
 </clothing>
 <clothing>
  <id>
   169501911
  </id>
  <name>
   Ellesse Shoes V-6942
  </name>
  <category>
   Shoes
  </category>
  <size>
   XXL
  </size>
  <color>
   Зеленый
  </color>
  <material>
   Лен
  </material>
  <price>
   376143
  </price>
  <rating>
   4.07
  </rating>
  <reviews>
   286764
  </reviews>
  <new>
   -
  </new>
  <sporty>
   no
  </sporty>
 </clothing>
 <clothing>
  <id>
   350398862
  </id>
  <name>
   Asics Sweater E-8045
  </name>
  <category>
   Sweater
  </category>
  <size>
   XL
  </size>
  <color>
   Оранжевый
  </color>
  <material>
   Лен
  </material>
  <price>
   575676
  </price>
  <rating>
   3.91
  </rating>
  <reviews>
   310018
  </reviews>
  <new>
   +
  </new>
  <sporty>
   yes
  </sporty>
 </clothing>
 <clothing>
  <id>
   539571424
  </id>
  <name>
   Fila Jeans I-5465
  </name>
  <category>
   Jeans
  </category>
  <size>
   M
  </size>
  <color>
   Желтый
  </color>
  <material>
   Кожа
  </material>
  <price>
   911204
  </price>
  <rating>
   1.07
  </rating>
  <reviews>
   21117
  </reviews>
  <new>
   -
  </new>
  <exclusive>
   no
  </exclusive>
  <sporty>
   yes
  </sporty>
 </clothing>
 <clothing>
  <id>
   503752218
  </id>
  <name>
   Adidas Socks U-1410
  </name>
  <category>
   Socks
  </category>
  <size>
   XL
  </size>
  <color>
   Зеленый
  </color>
  <material>
   Вискоза
  </material>
  <price>
   980600
  </price>
  <rating>
   1.68
  </rating>
  <reviews>
   253839
  </reviews>
  <new>
   +
  </new>
  <exclusive>
   no
  </exclusive>
 </clothing>
 <clothing>
  <id>
   570162004
  </id>
  <name>
   Vans Jacket T-7143
  </name>
  <category>
   Jacket
  </category>
  <size>
   M
  </size>
  <color>
   Желтый
  </color>
  <material>
   Лен
  </material>
  <price>
   483598
  </price>
  <rating>
   4.0
  </rating>
  <reviews>
   346642
  </reviews>
 </clothing>
 <clothing>
  <id>
   993156499
  </id>
  <name>
   Asics Handbags X-1647
  </name>
  <category>
   Handbags
  </category>
  <size>
   S
  </size>
  <color>
   Зеленый
  </color>
  <material>
   Полиэстер
  </material>
  <price>
   248798
  </price>
  <rating>
   3.52
  </rating>
  <reviews>
   24026
  </reviews>
  <new>
   -
  </new>
  <exclusive>
   yes
  </exclusive>
 </clothing>
 <clothing>
  <id>
   742763463
  </id>
  <name>
   Fila Dress E-1393
  </name>
  <category>
   Dress
  </category>
  <size>
   XL
  </size>
  <color>
   Красный
  </color>
  <material>
   Нейлон
  </material>
  <price>
   738315
  </price>
  <rating>
   3.37
  </rating>
  <reviews>
   828904
  </reviews>
  <new>
   -
  </new>
  <exclusive>
   yes
  </exclusive>
  <sporty>
   yes
  </sporty>
 </clothing>
 <clothing>
  <id>
   292898778
  </id>
  <name>
   Under Armour Socks M-6317
  </name>
  <category>
   Socks
  </category>
  <size>
   L
  </size>
  <color>
   Оранжевый
  </color>
  <material>
   Шерсть
  </material>
  <price>
   446463
  </price>
  <rating>
   3.34
  </rating>
  <reviews>
   396387
  </reviews>
  <new>
   +
  </new>
 </clothing>
 <clothing>
  <id>
   763543008
  </id>
  <name>
   Addidas Pants E-7471
  </name>
  <category>
   Pants
  </category>
  <size>
   M
  </size>
  <color>
   Оранжевый
  </color>
  <material>
   Шелк
  </material>
  <price>
   258991
  </price>
  <rating>
   2.7
  </rating>
  <reviews>
   214792
  </reviews>
  <new>
   +
  </new>
  <exclusive>
   no
  </exclusive>
  <sporty>
   no
  </sporty>
 </clothing>
</clothing-items>
